{
  "name": "no_mitigation",
  "data": [
    {
      "seriesName": "INDDST",
      "seriesValues": [
        [
          2020,
          0.014516552494197846
        ],
        [
          2021,
          0.014722403329140201
        ],
        [
          2022,
          0.0311891036418601
        ],
        [
          2023,
          0.0335461309342909
        ],
        [
          2024,
          0.0358858112883169
        ],
        [
          2025,
          0.0382124517529433
        ],
        [
          2026,
          0.0405313630726996
        ],
        [
          2027,
          0.0428440251656595
        ],
        [
          2028,
          0.0451590523764597
        ],
        [
          2029,
          0.0474854832086731
        ],
        [
          2030,
          0.0498229252273786
        ],
        [
          2031,
          0.0521759407338397
        ],
        [
          2032,
          0.0545447297113049
        ],
        [
          2033,
          0.056933102678880604
        ],
        [
          2034,
          0.0593434463333557
        ],
        [
          2035,
          0.0617739088746089
        ],
        [
          2036,
          0.0642241764080338
        ],
        [
          2037,
          0.0666938074933577
        ],
        [
          2038,
          0.0691829558078184
        ],
        [
          2039,
          0.07168967630818229
        ],
        [
          2040,
          0.07421344202927009
        ],
        [
          2041,
          0.0767546421872284
        ],
        [
          2042,
          0.079312422216503
        ],
        [
          2043,
          0.0818852641697219
        ],
        [
          2044,
          0.0844689174126516
        ],
        [
          2045,
          0.087063303270902
        ],
        [
          2046,
          0.0896690922644514
        ],
        [
          2047,
          0.0922853537523969
        ],
        [
          2048,
          0.09491208031573739
        ],
        [
          2049,
          0.0975467293667543
        ],
        [
          2050,
          0.1001906818998447
        ]
      ]
    },
    {
      "seriesName": "INDELC",
      "seriesValues": [
        [
          2020,
          0.1339897884754146
        ],
        [
          2021,
          0.1340140555151896
        ],
        [
          2022,
          0.2839059746893447
        ],
        [
          2023,
          0.3053613566237201
        ],
        [
          2024,
          0.3266588340696498
        ],
        [
          2025,
          0.3478376129292855
        ],
        [
          2026,
          0.3689460354736918
        ],
        [
          2027,
          0.3899975729968012
        ],
        [
          2028,
          0.411070639547922
        ],
        [
          2029,
          0.4322475101804047
        ],
        [
          2030,
          0.45352461266531513
        ],
        [
          2031,
          0.4749434763970871
        ],
        [
          2032,
          0.4965059217691251
        ],
        [
          2033,
          0.5182466349062353
        ],
        [
          2034,
          0.5401873412637435
        ],
        [
          2035,
          0.5623111844060084
        ],
        [
          2036,
          0.5846153070353338
        ],
        [
          2037,
          0.6070956908402984
        ],
        [
          2038,
          0.6297537347032451
        ],
        [
          2039,
          0.652571733421694
        ],
        [
          2040,
          0.6755448901741458
        ],
        [
          2041,
          0.6986767478899139
        ],
        [
          2042,
          0.7219595276898884
        ],
        [
          2043,
          0.7453794121097137
        ],
        [
          2044,
          0.7688977087756284
        ],
        [
          2045,
          0.7925137015359387
        ],
        [
          2046,
          0.8162334939526558
        ],
        [
          2047,
          0.8400486146533496
        ],
        [
          2048,
          0.863958996104853
        ],
        [
          2049,
          0.8879414938188795
        ],
        [
          2050,
          0.9120086786138888
        ]
      ]
    },
    {
      "seriesName": "INDGAS",
      "seriesValues": [
        [
          2020,
          0.52577301327401
        ],
        [
          2021,
          0.5052524243259449
        ],
        [
          2022,
          1.0703666972913337
        ],
        [
          2023,
          1.151256598693904
        ],
        [
          2024,
          1.231551177275351
        ],
        [
          2025,
          1.3113982449725234
        ],
        [
          2026,
          1.3909800591580421
        ],
        [
          2027,
          1.4703474085636739
        ],
        [
          2028,
          1.5497959255270939
        ],
        [
          2029,
          1.6296357989311647
        ],
        [
          2030,
          1.7098535609547434
        ],
        [
          2031,
          1.7906057834375453
        ],
        [
          2032,
          1.8718993295266946
        ],
        [
          2033,
          1.9538649709429776
        ],
        [
          2034,
          2.0365846158036445
        ],
        [
          2035,
          2.1199947129017755
        ],
        [
          2036,
          2.2040844898106795
        ],
        [
          2037,
          2.28883879691355
        ],
        [
          2038,
          2.374262908199696
        ],
        [
          2039,
          2.460290072488116
        ],
        [
          2040,
          2.546902205066107
        ],
        [
          2041,
          2.634112663290992
        ],
        [
          2042,
          2.721892119660408
        ],
        [
          2043,
          2.810188480329894
        ],
        [
          2044,
          2.8988558694391204
        ],
        [
          2045,
          2.987891586992328
        ],
        [
          2046,
          3.077318644303458
        ],
        [
          2047,
          3.167105103069919
        ],
        [
          2048,
          3.2572507086818674
        ],
        [
          2049,
          3.347668203062001
        ],
        [
          2050,
          3.438404980018956
        ]
      ]
    },
    {
      "seriesName": "INDKER",
      "seriesValues": [
        [
          2020,
          0.00046131535348044496
        ],
        [
          2021,
          0.00040185220005100393
        ],
        [
          2022,
          0.0008513154840210463
        ],
        [
          2023,
          0.000915651216568787
        ],
        [
          2024,
          0.000979513459482652
        ],
        [
          2025,
          0.0010430197748942732
        ],
        [
          2026,
          0.0011063151210911081
        ],
        [
          2027,
          0.0011694398928592383
        ],
        [
          2028,
          0.0012326292211937494
        ],
        [
          2029,
          0.001296129814628847
        ],
        [
          2030,
          0.0013599309615413993
        ],
        [
          2031,
          0.0014241571912463114
        ],
        [
          2032,
          0.001488813962343362
        ],
        [
          2033,
          0.0015540052840389829
        ],
        [
          2034,
          0.0016197963019030596
        ],
        [
          2035,
          0.0016861364705228722
        ],
        [
          2036,
          0.0017530172220553482
        ],
        [
          2037,
          0.0018204265072628014
        ],
        [
          2038,
          0.0018883685208087337
        ],
        [
          2039,
          0.001956790172183487
        ],
        [
          2040,
          0.0020256770777215332
        ],
        [
          2041,
          0.002095039861189572
        ],
        [
          2042,
          0.0021648551969761466
        ],
        [
          2043,
          0.0022350816522749904
        ],
        [
          2044,
          0.0023056032048113843
        ],
        [
          2045,
          0.0023764177071457374
        ],
        [
          2046,
          0.0024475434613121143
        ],
        [
          2047,
          0.0025189550652015263
        ],
        [
          2048,
          0.0025906523163101644
        ],
        [
          2049,
          0.0026625658139806147
        ],
        [
          2050,
          0.0027347332528492134
        ]
      ]
    },
    {
      "seriesName": "INDLPG",
      "seriesValues": [
        [
          2020,
          0.0693163521455435
        ],
        [
          2021,
          0.0762496283587665
        ],
        [
          2022,
          0.1615332434771547
        ],
        [
          2023,
          0.1737406562929415
        ],
        [
          2024,
          0.1858582266029248
        ],
        [
          2025,
          0.19790826128721
        ],
        [
          2026,
          0.2099182655219406
        ],
        [
          2027,
          0.2218959040341627
        ],
        [
          2028,
          0.2338857918614164
        ],
        [
          2029,
          0.2459347408266647
        ],
        [
          2030,
          0.2580407184481084
        ],
        [
          2031,
          0.2702273535972076
        ],
        [
          2032,
          0.2824956820184592
        ],
        [
          2033,
          0.2948654389860139
        ],
        [
          2034,
          0.3073489855756409
        ],
        [
          2035,
          0.3199367310250296
        ],
        [
          2036,
          0.3326270496249445
        ],
        [
          2037,
          0.3454176550871954
        ],
        [
          2038,
          0.3583093433302283
        ],
        [
          2039,
          0.371292040671071
        ],
        [
          2040,
          0.3843630178746794
        ],
        [
          2041,
          0.3975242907523233
        ],
        [
          2042,
          0.4107714333754042
        ],
        [
          2043,
          0.4240965840571891
        ],
        [
          2044,
          0.4374777280984866
        ],
        [
          2045,
          0.4509144580323324
        ],
        [
          2046,
          0.4644102465865173
        ],
        [
          2047,
          0.477960273826319
        ],
        [
          2048,
          0.4915645013275672
        ],
        [
          2049,
          0.5052097606310008
        ],
        [
          2050,
          0.51890320412248
        ]
      ]
    }
  ]
}