{
  "name": "no_mitigation",
  "data": [
    {
      "seriesName": "FT_IND",
      "seriesValues": [
        [
          2020,
          6.043711590934235
        ],
        [
          2021,
          6.385411793860928
        ],
        [
          2022,
          5.901373580131358
        ],
        [
          2023,
          6.040006664829203
        ],
        [
          2024,
          6.195817872318201
        ],
        [
          2025,
          6.343585855582305
        ],
        [
          2026,
          6.495834721391154
        ],
        [
          2027,
          6.459107350974513
        ],
        [
          2028,
          6.415751759847126
        ],
        [
          2029,
          6.371740903033805
        ],
        [
          2030,
          6.32704370717
        ],
        [
          2031,
          6.2817588763465135
        ],
        [
          2032,
          6.280472539716594
        ],
        [
          2033,
          6.30427731423218
        ],
        [
          2034,
          6.36874646296071
        ],
        [
          2035,
          6.43419689841591
        ],
        [
          2036,
          6.5002218158659
        ],
        [
          2037,
          6.56692308115391
        ],
        [
          2038,
          6.63461256043812
        ],
        [
          2039,
          6.70329399864691
        ],
        [
          2040,
          6.7729897328848
        ],
        [
          2041,
          6.84373436958306
        ],
        [
          2042,
          6.91534274092341
        ],
        [
          2043,
          6.98803097818604
        ],
        [
          2044,
          7.06178166886336
        ],
        [
          2045,
          7.13662689476063
        ],
        [
          2046,
          7.21261000698601
        ],
        [
          2047,
          7.28975712404775
        ],
        [
          2048,
          7.36810257490007
        ],
        [
          2049,
          7.44765344813058
        ],
        [
          2050,
          7.52846378098974
        ]
      ]
    },
    {
      "seriesName": "FT_SRV",
      "seriesValues": [
        [
          2022,
          1.14
        ],
        [
          2023,
          1.497
        ],
        [
          2024,
          1.87185
        ],
        [
          2025,
          2.2654425
        ],
        [
          2026,
          2.678714625
        ],
        [
          2027,
          3.11265035625
        ],
        [
          2028,
          3.5682828740625
        ],
        [
          2029,
          4.04669701776563
        ],
        [
          2030,
          4.54903186865391
        ],
        [
          2031,
          5.0764834620866
        ],
        [
          2032,
          5.63030763519093
        ],
        [
          2033,
          6.21182301695048
        ],
        [
          2034,
          6.822414167798
        ],
        [
          2035,
          7.4635348761879
        ],
        [
          2036,
          8.1367116199973
        ],
        [
          2037,
          8.84354720099717
        ],
        [
          2038,
          9.58572456104703
        ],
        [
          2039,
          10.3650107890994
        ],
        [
          2040,
          11.1832613285543
        ],
        [
          2041,
          12.0424243949821
        ],
        [
          2042,
          12.9445456147312
        ],
        [
          2043,
          13.8917728954677
        ],
        [
          2044,
          14.8863615402411
        ],
        [
          2045,
          15.9306796172532
        ],
        [
          2046,
          16.5271305042692
        ],
        [
          2048,
          17.7200322783013
        ]
      ]
    },
    {
      "seriesName": "FT_RSD",
      "seriesValues": [
        [
          2023,
          2.502
        ],
        [
          2024,
          3.2522
        ],
        [
          2026,
          0.699794474432122
        ],
        [
          2027,
          0.426744153390169
        ],
        [
          2028,
          0.32974730920956
        ],
        [
          2029,
          0.32819299051989
        ],
        [
          2031,
          0.225983551202392
        ],
        [
          2032,
          0.200303374248016
        ],
        [
          2033,
          0.161416822287423
        ],
        [
          2035,
          0.0968500933724537
        ],
        [
          2036,
          0.0645667289149703
        ]
      ]
    }
  ]
}