{
  "name": "no_mitigation",
  "data": [
    {
      "seriesName": "TRADST",
      "seriesValues": [
        [
          2020,
          4.50096460949688
        ],
        [
          2021,
          4.92691214565589
        ],
        [
          2022,
          4.51082269380828
        ],
        [
          2023,
          4.61209578421706
        ],
        [
          2024,
          4.71960919829414
        ],
        [
          2025,
          4.8311340543155
        ],
        [
          2026,
          4.94550366154912
        ],
        [
          2027,
          5.06177303588626
        ],
        [
          2028,
          5.18005475489547
        ],
        [
          2029,
          5.30041674866728
        ],
        [
          2030,
          5.42232096465234
        ],
        [
          2031,
          5.53670993620081
        ]
      ]
    },
    {
      "seriesName": "TRABDL",
      "seriesValues": [
        [
          2032,
          5.65172069040295
        ],
        [
          2033,
          5.76673555831497
        ],
        [
          2034,
          5.88123615373675
        ],
        [
          2035,
          5.9948981596409
        ],
        [
          2036,
          6.10765664967239
        ],
        [
          2037,
          6.21892085786122
        ],
        [
          2038,
          6.32904775414302
        ],
        [
          2039,
          6.43850454461968
        ],
        [
          2040,
          6.5477903487442
        ],
        [
          2041,
          6.65739894009788
        ],
        [
          2042,
          6.76777840291318
        ],
        [
          2043,
          6.87931957843322
        ],
        [
          2044,
          6.9923946534016
        ],
        [
          2045,
          7.10740829232971
        ],
        [
          2046,
          7.22485466592705
        ],
        [
          2047,
          7.34437521005775
        ],
        [
          2048,
          7.46664415863087
        ],
        [
          2049,
          7.59245084803413
        ],
        [
          2050,
          7.72262492492969
        ]
      ]
    }
  ]
}