{
  "name": "no_mitigation",
  "data": [
    {
      "seriesName": "DMD_TRA-P-BUS",
      "seriesValues": [
        [
          2020,
          3.245067527620002
        ],
        [
          2021,
          4.12458663036811
        ],
        [
          2022,
          4.73602090193219
        ],
        [
          2023,
          4.800353367431686
        ],
        [
          2024,
          4.864300196228028
        ],
        [
          2025,
          4.927950062479111
        ],
        [
          2026,
          4.991417568530063
        ],
        [
          2027,
          5.054844396834001
        ],
        [
          2028,
          5.11837379673289
        ],
        [
          2029,
          5.18216720738366
        ],
        [
          2030,
          5.24633888067334
        ],
        [
          2031,
          5.2993284489067
        ],
        [
          2032,
          5.352723468423235
        ],
        [
          2033,
          5.40642053339925
        ],
        [
          2034,
          5.46025113178789
        ],
        [
          2035,
          5.514102233502286
        ],
        [
          2036,
          5.567889732556509
        ],
        [
          2037,
          5.62162803949027
        ],
        [
          2038,
          5.67532785849735
        ],
        [
          2039,
          5.72899991791689
        ],
        [
          2040,
          5.78263707449206
        ],
        [
          2041,
          5.84137942706219
        ],
        [
          2042,
          5.900121779632335
        ],
        [
          2043,
          5.95886413220247
        ],
        [
          2044,
          6.01760648477261
        ],
        [
          2045,
          6.07634883734274
        ],
        [
          2046,
          6.13154228531051
        ],
        [
          2047,
          6.18673573327827
        ],
        [
          2048,
          6.24192918124603
        ],
        [
          2049,
          6.2971226292138
        ],
        [
          2050,
          6.352316077181563
        ]
      ]
    },
    {
      "seriesName": "DMD_TRA-P-CAR",
      "seriesValues": [
        [
          2020,
          14.712300017860011
        ],
        [
          2021,
          18.6998130051659
        ],
        [
          2022,
          21.471898444956413
        ],
        [
          2023,
          21.763565267067623
        ],
        [
          2024,
          22.05348371173322
        ],
        [
          2025,
          22.34205580473663
        ],
        [
          2026,
          22.6298011235811
        ],
        [
          2027,
          22.917362020001978
        ],
        [
          2028,
          23.20538794960491
        ],
        [
          2029,
          23.4946108359296
        ],
        [
          2030,
          23.785548667592618
        ],
        [
          2031,
          24.025789716208884
        ],
        [
          2032,
          24.267868976470982
        ],
        [
          2033,
          24.51131763301865
        ],
        [
          2034,
          24.7553716956519
        ],
        [
          2035,
          24.999518715080878
        ],
        [
          2036,
          25.243377376437202
        ],
        [
          2037,
          25.48701301339448
        ],
        [
          2038,
          25.730474156009493
        ],
        [
          2039,
          25.97380944380727
        ],
        [
          2040,
          26.21698649110201
        ],
        [
          2041,
          26.48330918158867
        ],
        [
          2042,
          26.74963186352776
        ],
        [
          2043,
          27.015954562562122
        ],
        [
          2044,
          27.28227725304877
        ],
        [
          2045,
          27.548599943535496
        ],
        [
          2046,
          27.79883281499669
        ],
        [
          2047,
          28.04906568645791
        ],
        [
          2048,
          28.29929855791913
        ],
        [
          2049,
          28.549531429380387
        ],
        [
          2050,
          28.79976430084159
        ]
      ]
    },
    {
      "seriesName": "DMD_TRA-P-HPT",
      "seriesValues": [
        [
          2020,
          1.6922131279000001
        ],
        [
          2021,
          2.1508580587809183
        ],
        [
          2022,
          2.4697041513143327
        ],
        [
          2023,
          2.503251756022658
        ],
        [
          2024,
          2.5365982618367022
        ],
        [
          2025,
          2.569789909881745
        ],
        [
          2026,
          2.6028864621169063
        ],
        [
          2027,
          2.6359618020299997
        ],
        [
          2028,
          2.669090630198137
        ],
        [
          2029,
          2.702357132684733
        ],
        [
          2030,
          2.73582088869468
        ],
        [
          2031,
          2.763453485626197
        ],
        [
          2032,
          2.791297514208433
        ],
        [
          2033,
          2.81929905115911
        ],
        [
          2034,
          2.847370222097977
        ],
        [
          2035,
          2.875452084955173
        ],
        [
          2036,
          2.903500780781
        ],
        [
          2037,
          2.931523824274067
        ],
        [
          2038,
          2.959526797375913
        ],
        [
          2039,
          2.9875152946192403
        ],
        [
          2040,
          3.015485590992787
        ],
        [
          2041,
          3.046118106136723
        ],
        [
          2042,
          3.07675062128066
        ],
        [
          2043,
          3.1073831364245974
        ],
        [
          2044,
          3.138015651568533
        ],
        [
          2045,
          3.1686481667124697
        ],
        [
          2046,
          3.1974300260821664
        ],
        [
          2047,
          3.226211885451863
        ],
        [
          2048,
          3.25499374482155
        ],
        [
          2049,
          3.28377560419125
        ],
        [
          2050,
          3.31255746356094
        ]
      ]
    },
    {
      "seriesName": "DMD_TRA-P-TAXI",
      "seriesValues": [
        [
          2020,
          0.25880906662
        ],
        [
          2021,
          0.3289547619311995
        ],
        [
          2022,
          0.37771945843631
        ],
        [
          2023,
          0.382850268568171
        ],
        [
          2024,
          0.387950322398554
        ],
        [
          2025,
          0.393026692099561
        ],
        [
          2026,
          0.39808851773552656
        ],
        [
          2027,
          0.4031470991340002
        ],
        [
          2028,
          0.40821386108912633
        ],
        [
          2029,
          0.4133016791164885
        ],
        [
          2030,
          0.418419665329775
        ],
        [
          2031,
          0.4226458272134177
        ],
        [
          2032,
          0.4269043257024663
        ],
        [
          2033,
          0.4311869137066883
        ],
        [
          2034,
          0.435480151614985
        ],
        [
          2035,
          0.439775024757851
        ],
        [
          2036,
          0.444064825295918
        ],
        [
          2037,
          0.4483507025360335
        ],
        [
          2038,
          0.452633510186905
        ],
        [
          2039,
          0.45691410388294146
        ],
        [
          2040,
          0.4611919139165443
        ],
        [
          2041,
          0.4658768868209109
        ],
        [
          2042,
          0.4705618597252777
        ],
        [
          2043,
          0.475246832629645
        ],
        [
          2044,
          0.479931805534011
        ],
        [
          2045,
          0.484616778438378
        ],
        [
          2046,
          0.48901870987139
        ],
        [
          2047,
          0.493420641304402
        ],
        [
          2048,
          0.497822572737414
        ],
        [
          2049,
          0.502224504170426
        ],
        [
          2050,
          0.506626435603437
        ]
      ]
    }
  ]
}