{
  "name": "mitigation_cb",
  "data": [
    {
      "seriesName": "FT_AGR",
      "seriesValues": [
        [
          2020,
          10.690022677149742
        ],
        [
          2021,
          10.655923801764901
        ],
        [
          2022,
          10.613413736206155
        ],
        [
          2023,
          10.727274630100686
        ],
        [
          2024,
          10.811769513102142
        ],
        [
          2025,
          10.93280176443334
        ],
        [
          2026,
          10.977549882960542
        ],
        [
          2027,
          11.022979851513766
        ],
        [
          2028,
          11.09485034707237
        ],
        [
          2029,
          11.160210275668664
        ],
        [
          2030,
          11.163676991873778
        ],
        [
          2031,
          10.778222012051563
        ],
        [
          2032,
          10.71906365665613
        ],
        [
          2033,
          10.711720847119443
        ],
        [
          2034,
          10.730693856814016
        ],
        [
          2035,
          10.638085395907629
        ],
        [
          2036,
          10.59766340487187
        ],
        [
          2037,
          10.557436474226447
        ],
        [
          2038,
          10.509888022412126
        ],
        [
          2039,
          10.457570877234552
        ],
        [
          2040,
          10.784231725302694
        ],
        [
          2041,
          11.211127005144167
        ],
        [
          2042,
          11.195981419777702
        ],
        [
          2043,
          11.180704779058741
        ],
        [
          2044,
          11.165296324135781
        ],
        [
          2045,
          11.154094629364314
        ],
        [
          2046,
          11.134813385506684
        ],
        [
          2047,
          11.119720870626786
        ],
        [
          2048,
          11.104477383138322
        ],
        [
          2049,
          11.089082546297712
        ],
        [
          2050,
          11.073535988566523
        ]
      ]
    },
    {
      "seriesName": "FT_IND",
      "seriesValues": [
        [
          2020,
          90.8727004768746
        ],
        [
          2021,
          92.46786638799064
        ],
        [
          2022,
          99.55731211567303
        ],
        [
          2023,
          101.44037566965103
        ],
        [
          2024,
          103.3457463991571
        ],
        [
          2025,
          105.27676024629156
        ],
        [
          2026,
          107.23714381825077
        ],
        [
          2027,
          108.36610294140044
        ],
        [
          2028,
          109.49746267629047
        ],
        [
          2029,
          110.63511962436952
        ],
        [
          2030,
          111.77914465960801
        ],
        [
          2031,
          112.93304838293673
        ],
        [
          2032,
          114.28633545585295
        ],
        [
          2033,
          115.65171197921299
        ],
        [
          2034,
          117.03033682743482
        ],
        [
          2035,
          118.42169092971396
        ],
        [
          2036,
          119.82587350885673
        ],
        [
          2037,
          121.19382624031735
        ],
        [
          2038,
          122.57419847231205
        ],
        [
          2039,
          123.96646378243247
        ],
        [
          2040,
          125.3706613520323
        ],
        [
          2041,
          126.78718814455733
        ],
        [
          2042,
          128.18101606618902
        ],
        [
          2043,
          129.58634141290565
        ],
        [
          2044,
          131.52389835279197
        ],
        [
          2045,
          132.74373230052188
        ],
        [
          2046,
          133.86441949972178
        ],
        [
          2047,
          135.3124158048702
        ],
        [
          2048,
          136.7715345631602
        ],
        [
          2049,
          138.2411215316367
        ],
        [
          2050,
          139.72198331643685
        ]
      ]
    },
    {
      "seriesName": "FT_RSD",
      "seriesValues": [
        [
          2020,
          123.93403873646614
        ],
        [
          2021,
          127.33981531593605
        ],
        [
          2022,
          123.76182416119498
        ],
        [
          2023,
          118.70563024014523
        ],
        [
          2024,
          118.88080869372874
        ],
        [
          2025,
          123.463620448284
        ],
        [
          2026,
          131.60239526227892
        ],
        [
          2027,
          129.675057414836
        ],
        [
          2028,
          135.44769494969916
        ],
        [
          2029,
          136.80437430723148
        ],
        [
          2030,
          134.13626892896835
        ],
        [
          2031,
          128.80231046583287
        ],
        [
          2032,
          126.7862128824783
        ],
        [
          2033,
          127.99028328051075
        ],
        [
          2034,
          129.03970594327618
        ],
        [
          2035,
          130.88819501411248
        ],
        [
          2036,
          135.10361514573276
        ],
        [
          2037,
          140.22826023607553
        ],
        [
          2038,
          145.60486126119417
        ],
        [
          2039,
          153.1965204130181
        ],
        [
          2040,
          160.67360294166252
        ],
        [
          2041,
          169.41281586818056
        ],
        [
          2042,
          179.86492678642577
        ],
        [
          2043,
          191.71561844761862
        ],
        [
          2044,
          205.02043440962908
        ],
        [
          2045,
          219.8818254249524
        ],
        [
          2046,
          236.0335111671107
        ],
        [
          2047,
          253.82714308583894
        ],
        [
          2048,
          273.3545136448136
        ],
        [
          2049,
          294.78870042812434
        ],
        [
          2050,
          317.995669172062
        ]
      ]
    },
    {
      "seriesName": "FT_SRV",
      "seriesValues": [
        [
          2020,
          73.71959127750013
        ],
        [
          2021,
          78.0945028731946
        ],
        [
          2022,
          83.83206774967272
        ],
        [
          2023,
          89.97656514332249
        ],
        [
          2024,
          94.6517170758715
        ],
        [
          2025,
          99.94702386877944
        ],
        [
          2026,
          105.66811281330729
        ],
        [
          2027,
          108.00431940523566
        ],
        [
          2028,
          113.23355606240165
        ],
        [
          2029,
          118.4931374017695
        ],
        [
          2030,
          124.540324590531
        ],
        [
          2031,
          130.3316829528256
        ],
        [
          2032,
          132.84317016005636
        ],
        [
          2033,
          135.3098809817652
        ],
        [
          2034,
          134.84474011462868
        ],
        [
          2035,
          134.86167288437656
        ],
        [
          2036,
          136.1516695577866
        ],
        [
          2037,
          137.26456836876864
        ],
        [
          2038,
          138.04354971815354
        ],
        [
          2039,
          134.85821086834233
        ],
        [
          2040,
          135.24605157911682
        ],
        [
          2041,
          135.74969815163422
        ],
        [
          2042,
          136.56311650004176
        ],
        [
          2043,
          136.86955457278304
        ],
        [
          2044,
          135.3077731212918
        ],
        [
          2045,
          134.90040272948025
        ],
        [
          2046,
          134.63448559601582
        ],
        [
          2047,
          134.81150866076828
        ],
        [
          2048,
          134.97787777760902
        ],
        [
          2049,
          135.00533385551915
        ],
        [
          2050,
          134.90624690239432
        ]
      ]
    },
    {
      "seriesName": "FT_TRA",
      "seriesValues": [
        [
          2020,
          163.00654134429845
        ],
        [
          2021,
          177.71702311190487
        ],
        [
          2022,
          242.96867613820456
        ],
        [
          2023,
          245.79478914109922
        ],
        [
          2024,
          247.10029007507757
        ],
        [
          2025,
          246.1181560939103
        ],
        [
          2026,
          324.23115958556684
        ],
        [
          2027,
          232.71944541593615
        ],
        [
          2028,
          221.57620347874504
        ],
        [
          2029,
          215.03078158798678
        ],
        [
          2030,
          214.28449635482184
        ],
        [
          2031,
          220.07389406637128
        ],
        [
          2032,
          211.78383107137918
        ],
        [
          2033,
          200.79324306874946
        ],
        [
          2034,
          189.41323696862761
        ],
        [
          2035,
          179.25400280381706
        ],
        [
          2036,
          171.76304513622782
        ],
        [
          2037,
          166.15380161934985
        ],
        [
          2038,
          160.92088546109838
        ],
        [
          2039,
          158.77900126080857
        ],
        [
          2040,
          157.66611231117992
        ],
        [
          2041,
          157.5909316183614
        ],
        [
          2042,
          156.80359218854193
        ],
        [
          2043,
          157.16433017486082
        ],
        [
          2044,
          157.69074808692903
        ],
        [
          2045,
          157.99039659647966
        ],
        [
          2046,
          158.69154841974836
        ],
        [
          2047,
          158.49029850649407
        ],
        [
          2048,
          159.49551730096596
        ],
        [
          2049,
          160.09585727217672
        ],
        [
          2050,
          161.19511392929286
        ]
      ]
    }
  ]
}