{
  "name": "mitigation_cb",
  "data": [
    {
      "seriesName": "PRC_AGR",
      "seriesValues": [
        [
          2020,
          31.29958037750148
        ],
        [
          2021,
          63.83859424384495
        ],
        [
          2022,
          109.33970328271462
        ],
        [
          2023,
          288.8623562522656
        ],
        [
          2024,
          560.4751432840293
        ],
        [
          2025,
          946.3677104775243
        ],
        [
          2026,
          1382.932908389395
        ],
        [
          2027,
          1900.6089991588824
        ],
        [
          2028,
          2478.534790852766
        ],
        [
          2029,
          3160.5071178496846
        ],
        [
          2030,
          3877.4523290462157
        ],
        [
          2031,
          4335.207598654637
        ],
        [
          2032,
          4791.450097196685
        ],
        [
          2033,
          5286.077256345108
        ],
        [
          2034,
          5840.16519494091
        ],
        [
          2035,
          6398.689188362862
        ],
        [
          2036,
          6957.623312357536
        ],
        [
          2037,
          7517.065068178838
        ],
        [
          2038,
          8082.3497493395225
        ],
        [
          2039,
          8643.782950506265
        ],
        [
          2040,
          9516.885362491452
        ],
        [
          2041,
          10771.005533555843
        ],
        [
          2042,
          12049.865117986195
        ],
        [
          2043,
          13353.464115782504
        ],
        [
          2044,
          14681.802526944772
        ],
        [
          2045,
          16037.358622549622
        ],
        [
          2046,
          17415.175860443807
        ],
        [
          2047,
          18817.732511703947
        ],
        [
          2048,
          20245.02857633005
        ],
        [
          2049,
          21697.064054322105
        ],
        [
          2050,
          23173.838945680123
        ]
      ]
    },
    {
      "seriesName": "PRC_IND",
      "seriesValues": [
        [
          2020,
          0.0
        ],
        [
          2021,
          0.0
        ],
        [
          2022,
          0.0
        ],
        [
          2023,
          0.0
        ],
        [
          2024,
          0.0
        ],
        [
          2025,
          0.0
        ],
        [
          2026,
          0.0
        ],
        [
          2027,
          0.0
        ],
        [
          2028,
          0.0
        ],
        [
          2029,
          0.0
        ],
        [
          2030,
          107.313602090015
        ],
        [
          2031,
          214.64327234492848
        ],
        [
          2032,
          322.9230322722325
        ],
        [
          2033,
          432.16129213148884
        ],
        [
          2034,
          542.3665366304601
        ],
        [
          2035,
          653.5473255841285
        ],
        [
          2036,
          765.7122945795527
        ],
        [
          2037,
          878.629616261205
        ],
        [
          2038,
          992.3043370760242
        ],
        [
          2039,
          1106.7415373202705
        ],
        [
          2040,
          1221.946331366568
        ],
        [
          2041,
          1337.9238678924771
        ],
        [
          2042,
          1454.5082287046976
        ],
        [
          2043,
          1571.7025888638964
        ],
        [
          2044,
          1689.5101400434742
        ],
        [
          2045,
          1807.9340906164869
        ],
        [
          2046,
          1926.9776657430234
        ],
        [
          2047,
          2046.6459816719414
        ],
        [
          2048,
          2166.9423170436016
        ],
        [
          2049,
          2287.869967704674
        ],
        [
          2050,
          2409.432246798433
        ]
      ]
    },
    {
      "seriesName": "PRC_PWR",
      "seriesValues": [
        [
          2020,
          109.38685622999024
        ],
        [
          2021,
          260.2677109352323
        ],
        [
          2022,
          450.300427563506
        ],
        [
          2023,
          928.8278475832428
        ],
        [
          2024,
          1508.800492000661
        ],
        [
          2025,
          2195.145278229531
        ],
        [
          2026,
          3246.1704724281685
        ],
        [
          2027,
          4458.899504981819
        ],
        [
          2028,
          6256.258465041844
        ],
        [
          2029,
          8580.787776960675
        ],
        [
          2030,
          11425.120867943762
        ],
        [
          2031,
          14325.82924207631
        ],
        [
          2032,
          17318.06018249168
        ],
        [
          2033,
          20818.579352058892
        ],
        [
          2034,
          24522.58866134891
        ],
        [
          2035,
          28572.80423647759
        ],
        [
          2036,
          32919.67034632235
        ],
        [
          2037,
          37437.80067585445
        ],
        [
          2038,
          42224.80747878006
        ],
        [
          2039,
          47368.956198246306
        ],
        [
          2040,
          52654.601501222394
        ],
        [
          2041,
          58207.00136474349
        ],
        [
          2042,
          63949.0491634911
        ],
        [
          2043,
          69795.07931160374
        ],
        [
          2044,
          75709.00918531604
        ],
        [
          2045,
          81681.56994665702
        ],
        [
          2046,
          87703.34935659931
        ],
        [
          2047,
          93819.15322953627
        ],
        [
          2048,
          100062.72871698474
        ],
        [
          2049,
          106466.24914940872
        ],
        [
          2050,
          112963.4161457668
        ]
      ]
    },
    {
      "seriesName": "PRC_RSD",
      "seriesValues": [
        [
          2020,
          316.1132212793769
        ],
        [
          2021,
          772.7116593141911
        ],
        [
          2022,
          1376.0854668350296
        ],
        [
          2023,
          2196.68680828137
        ],
        [
          2024,
          3204.8644952897566
        ],
        [
          2025,
          4324.837068323668
        ],
        [
          2026,
          5553.560134107749
        ],
        [
          2027,
          6892.480197407111
        ],
        [
          2028,
          8347.338082350969
        ],
        [
          2029,
          9872.068020895389
        ],
        [
          2030,
          11496.82806365068
        ],
        [
          2031,
          13235.528965996327
        ],
        [
          2032,
          15086.808443752921
        ],
        [
          2033,
          17025.606953546023
        ],
        [
          2034,
          19059.809993517894
        ],
        [
          2035,
          21190.536497900677
        ],
        [
          2036,
          23401.942070833444
        ],
        [
          2037,
          25692.208638302327
        ],
        [
          2038,
          28067.77402637594
        ],
        [
          2039,
          30462.80980654317
        ],
        [
          2040,
          32894.59207071537
        ],
        [
          2041,
          35342.105981665954
        ],
        [
          2042,
          37806.751830428606
        ],
        [
          2043,
          40261.84980877075
        ],
        [
          2044,
          42710.81021491705
        ],
        [
          2045,
          45177.59099719669
        ],
        [
          2046,
          47665.876803017185
        ],
        [
          2047,
          50176.24399028894
        ],
        [
          2048,
          52708.01009237418
        ],
        [
          2049,
          55256.46977559946
        ],
        [
          2050,
          57824.95794162513
        ]
      ]
    },
    {
      "seriesName": "PRC_SRV",
      "seriesValues": [
        [
          2020,
          253.83256868848534
        ],
        [
          2021,
          678.642472233915
        ],
        [
          2022,
          1151.9024931333547
        ],
        [
          2023,
          1795.0444620064318
        ],
        [
          2024,
          2569.5161663828003
        ],
        [
          2025,
          3432.928630086256
        ],
        [
          2026,
          4368.86676950428
        ],
        [
          2027,
          5359.79278234637
        ],
        [
          2028,
          6409.378847038096
        ],
        [
          2029,
          7484.8129584133685
        ],
        [
          2030,
          8591.055389984038
        ],
        [
          2031,
          9691.552575899368
        ],
        [
          2032,
          10817.42813696685
        ],
        [
          2033,
          11968.746513875953
        ],
        [
          2034,
          13128.423707621565
        ],
        [
          2035,
          14314.737858434062
        ],
        [
          2036,
          15524.815925527697
        ],
        [
          2037,
          16758.971777688334
        ],
        [
          2038,
          18015.035484865293
        ],
        [
          2039,
          19291.091877763352
        ],
        [
          2040,
          20584.06111465892
        ],
        [
          2041,
          21863.859980303194
        ],
        [
          2042,
          23060.513923425624
        ],
        [
          2043,
          24241.75211332767
        ],
        [
          2044,
          25437.86289127436
        ],
        [
          2045,
          26639.679937622743
        ],
        [
          2046,
          27867.594507449783
        ],
        [
          2047,
          29117.573918346538
        ],
        [
          2048,
          30389.748758090063
        ],
        [
          2049,
          31682.956166233445
        ],
        [
          2050,
          33005.847550725484
        ]
      ]
    },
    {
      "seriesName": "PRC_SUP",
      "seriesValues": [
        [
          2020,
          26304.955650778673
        ],
        [
          2021,
          75266.7586089356
        ],
        [
          2022,
          81487.18574676721
        ],
        [
          2023,
          88011.26975728458
        ],
        [
          2024,
          94594.65869021733
        ],
        [
          2025,
          119926.80481455689
        ],
        [
          2026,
          142923.28919940547
        ],
        [
          2027,
          148932.34422211017
        ],
        [
          2028,
          154623.5651256019
        ],
        [
          2029,
          160055.98696598623
        ],
        [
          2030,
          178410.83948038172
        ],
        [
          2031,
          183798.85875446475
        ],
        [
          2032,
          189008.87292490446
        ],
        [
          2033,
          193760.0720107095
        ],
        [
          2034,
          198169.6029458783
        ],
        [
          2035,
          202148.9283683577
        ],
        [
          2036,
          205840.77184692147
        ],
        [
          2037,
          209327.27406141008
        ],
        [
          2038,
          212595.8864249209
        ],
        [
          2039,
          215651.47553836487
        ],
        [
          2040,
          218632.70520352686
        ],
        [
          2041,
          221508.77082828572
        ],
        [
          2042,
          224423.89774328444
        ],
        [
          2043,
          227288.1856345525
        ],
        [
          2044,
          230240.75974511815
        ],
        [
          2045,
          233300.0577151393
        ],
        [
          2046,
          236306.47616025072
        ],
        [
          2047,
          239275.51706233682
        ],
        [
          2048,
          242149.26201412268
        ],
        [
          2049,
          244989.03271731618
        ],
        [
          2050,
          247791.42004665983
        ]
      ]
    },
    {
      "seriesName": "PRC_TRA",
      "seriesValues": [
        [
          2020,
          3027.9985114492274
        ],
        [
          2021,
          6309.566378003721
        ],
        [
          2022,
          9933.376367464685
        ],
        [
          2023,
          13946.95989373406
        ],
        [
          2024,
          18352.833838289596
        ],
        [
          2025,
          23129.557358904145
        ],
        [
          2026,
          28337.72269552984
        ],
        [
          2027,
          34637.4423825469
        ],
        [
          2028,
          42109.016808628796
        ],
        [
          2029,
          50334.78748047749
        ],
        [
          2030,
          58526.147326028644
        ],
        [
          2031,
          66309.39990862158
        ],
        [
          2032,
          74952.08357662673
        ],
        [
          2033,
          84543.90752635099
        ],
        [
          2034,
          94861.47971260066
        ],
        [
          2035,
          106008.20417544179
        ],
        [
          2036,
          117854.85029623532
        ],
        [
          2037,
          130304.31090077758
        ],
        [
          2038,
          143286.07906412127
        ],
        [
          2039,
          156721.54444575234
        ],
        [
          2040,
          170602.7825935464
        ],
        [
          2041,
          184891.46710832286
        ],
        [
          2042,
          199596.79710312595
        ],
        [
          2043,
          214648.53733012584
        ],
        [
          2044,
          230013.8518558937
        ],
        [
          2045,
          245733.23760718937
        ],
        [
          2046,
          261672.49939561868
        ],
        [
          2047,
          277684.5997116367
        ],
        [
          2048,
          293832.4815831598
        ],
        [
          2049,
          310150.23025750753
        ],
        [
          2050,
          326642.05796546367
        ]
      ]
    }
  ]
}