{
  "name": "mitigation_cb",
  "data": [
    {
      "seriesName": "DMD_TRA-F-MTRUCK-HEV",
      "seriesValues": [
        [
          2020,
          0.19875
        ],
        [
          2021,
          0.377625
        ],
        [
          2022,
          0.6459375
        ],
        [
          2023,
          1.0485064885
        ],
        [
          2024,
          1.652359971250001
        ],
        [
          2025,
          2.558140195374995
        ],
        [
          2026,
          3.9168105315624957
        ],
        [
          2027,
          4.809392764213401
        ],
        [
          2028,
          5.30942067247531
        ],
        [
          2029,
          5.475560221379213
        ],
        [
          2030,
          6.8136035917044655
        ],
        [
          2031,
          6.539832263927493
        ],
        [
          2032,
          7.955892260366729
        ],
        [
          2033,
          9.53956939735346
        ],
        [
          2034,
          11.221837286413699
        ],
        [
          2035,
          12.538891125258568
        ],
        [
          2036,
          13.096501657058669
        ],
        [
          2037,
          12.916398691317069
        ],
        [
          2038,
          11.828693430751168
        ],
        [
          2039,
          10.73213891072892
        ],
        [
          2040,
          9.671887950548458
        ],
        [
          2041,
          8.67317831692955
        ],
        [
          2042,
          7.68711628626838
        ],
        [
          2043,
          6.72170734752533
        ],
        [
          2044,
          5.7534026613473
        ],
        [
          2045,
          4.84961026238309
        ],
        [
          2046,
          3.92720917243991
        ],
        [
          2047,
          3.22524092458656
        ],
        [
          2048,
          2.72742052267421
        ],
        [
          2049,
          2.41411663339832
        ],
        [
          2050,
          1.99964038783281
        ]
      ]
    },
    {
      "seriesName": "DMD_TRA-F-MTRUCK-ICE",
      "seriesValues": [
        [
          2020,
          12.125814733178842
        ],
        [
          2021,
          12.029389041699604
        ],
        [
          2022,
          12.647522249481215
        ],
        [
          2023,
          12.450785673191248
        ],
        [
          2024,
          12.367745898510892
        ],
        [
          2025,
          11.802763899219585
        ],
        [
          2026,
          11.081972824356896
        ],
        [
          2027,
          10.423427706652186
        ],
        [
          2028,
          9.842704978091188
        ],
        [
          2029,
          9.269284546714365
        ],
        [
          2030,
          8.670511193266055
        ],
        [
          2031,
          7.903846854369675
        ],
        [
          2032,
          6.931160720981563
        ],
        [
          2033,
          5.816650278198434
        ],
        [
          2034,
          4.627289103221784
        ],
        [
          2035,
          3.467963136920572
        ],
        [
          2036,
          2.467783783248716
        ],
        [
          2037,
          1.73034997693889
        ],
        [
          2038,
          1.229357750286444
        ],
        [
          2039,
          0.8161277938733063
        ],
        [
          2040,
          0.6180928398000309
        ],
        [
          2041,
          0.476032821868693
        ],
        [
          2042,
          0.2449404662749636
        ],
        [
          2043,
          0.148623701076246
        ],
        [
          2044,
          0.0340936740179888
        ]
      ]
    },
    {
      "seriesName": "DMD_TRA-F-MTRUCK-BEV",
      "seriesValues": [
        [
          2025,
          0.0796002385
        ],
        [
          2026,
          0.19900059625
        ],
        [
          2027,
          0.378101132875
        ],
        [
          2028,
          0.6467519378125
        ],
        [
          2029,
          1.04972814521875
        ],
        [
          2030,
          1.65419245632813
        ],
        [
          2031,
          1.58080340965221
        ],
        [
          2032,
          1.47869065291563
        ],
        [
          2033,
          1.36897111910984
        ],
        [
          2034,
          1.26034642880194
        ],
        [
          2035,
          1.50824975519836
        ],
        [
          2036,
          2.34197487129754
        ],
        [
          2037,
          3.59256254544631
        ],
        [
          2038,
          5.46844405666947
        ],
        [
          2039,
          7.39818865363801
        ],
        [
          2040,
          9.07471856306825
        ],
        [
          2041,
          10.6203221123059
        ],
        [
          2042,
          12.3159382663451
        ],
        [
          2043,
          13.8666166878872
        ],
        [
          2044,
          15.4488539462956
        ],
        [
          2045,
          16.8988371033811
        ],
        [
          2046,
          18.3462651095315
        ],
        [
          2047,
          19.5852597456874
        ],
        [
          2048,
          20.6308478602355
        ],
        [
          2049,
          23.9156244152856
        ],
        [
          2050,
          24.4834282873567
        ]
      ]
    },
    {
      "seriesName": "DMD_TRA-F-MTRUCK-FCV",
      "seriesValues": [
        [
          2036,
          0.0366034758176915
        ],
        [
          2037,
          0.134505452226537
        ],
        [
          2038,
          0.281358416839806
        ],
        [
          2039,
          0.271674153580373
        ],
        [
          2040,
          0.255326455539835
        ],
        [
          2041,
          0.237429862611769
        ],
        [
          2042,
          0.220190880909395
        ],
        [
          2043,
          0.202639541253126
        ],
        [
          2044,
          0.184847503469076
        ],
        [
          2045,
          0.165437968423832
        ],
        [
          2046,
          0.144430414902932
        ],
        [
          2047,
          0.123015834628446
        ],
        [
          2048,
          0.10271900160555
        ],
        [
          2049,
          0.0849656790734476
        ],
        [
          2050,
          0.0691753791726535
        ]
      ]
    }
  ]
}